groove/.DS_Store
groove/__init__.py
groove/assets/.DS_Store
groove/assets/__init__.py
groove/cli.py
groove/dialer.py
groove/enums.py
groove/models.py
groove/proxy.py
groove/tape.py
groove/tests/__init__.py
groove/tests/conftest.py
groove/tests/mock_server.py
groove/tests/test_auth.py
groove/tests/test_cache.py
groove/tests/test_end_proxy.py
groove/tests/test_fingerprint.py
groove/tests/test_tape.py
groove-1.0.4.dist-info/WHEEL
groove-1.0.4.dist-info/entry_points.txt
groove-1.0.4.dist-info/METADATA
groove-1.0.4.dist-info/RECORD
