Metadata-Version: 2.1
Name: groove
Version: 1.0.4
Summary: 
Author: Pierce Freeman
Author-email: pierce@freeman.vc
Requires-Python: >=3.10,<4.0
Classifier: Programming Language :: Python :: 3
Classifier: Programming Language :: Python :: 3.10
Classifier: Programming Language :: Python :: 3.11
Requires-Dist: beautifulsoup4 (>=4.11.1,<5.0.0)
Requires-Dist: pydantic (>=1.10.2,<2.0.0)
Requires-Dist: pyhumps (>=3.8.0,<4.0.0)
Requires-Dist: requests (>=2.28.1,<3.0.0)
